thcon/__init__.py
thcon/thcon.py
thcon-0.0.2.dist-info/METADATA
thcon-0.0.2.dist-info/WHEEL
thcon-0.0.2.dist-info/top_level.txt
thcon-0.0.2.dist-info/RECORD
