Metadata-Version: 2.1
Name: thcon
Version: 0.0.2
Summary: zxczxczxc
Author: asd dasd
Requires-Python: >=3.6
Requires-Dist: pyperclip
Requires-Dist: mistralai
